nvtx/__init__.py
nvtx/nvtx.py
nvtx/colors.py
nvtx/__main__.py
nvtx/_lib/__init__.py
nvtx/_lib/profiler.pxd
nvtx/_lib/lib.pxd
nvtx/_lib/lib.cpython-312-x86_64-linux-gnu.so
nvtx/_lib/lib.pyx
nvtx/_lib/profiler.cpython-312-x86_64-linux-gnu.so
nvtx/_lib/__init__.pxd
nvtx/_lib/profiler.pyx
nvtx-0.2.13.dist-info/METADATA
nvtx-0.2.13.dist-info/RECORD
nvtx-0.2.13.dist-info/top_level.txt
nvtx-0.2.13.dist-info/WHEEL
nvtx-0.2.13.dist-info/licenses/LICENSE.txt
