Metadata-Version: 2.4
Name: nvtx
Version: 0.2.13
Summary: Python NVTX - Python code annotation library
Author: NVIDIA Corporation
License: Apache 2.0
Project-URL: Homepage, https://github.com/NVIDIA/NVTX
Project-URL: Documentation, https://nvidia.github.io/NVTX/python/
Project-URL: Repository, https://github.com/NVIDIA/NVTX
Project-URL: License, https://nvidia.github.io/NVTX/LICENSE.txt
Project-URL: Issues, https://github.com/NVIDIA/NVTX/issues
Classifier: Intended Audience :: Developers
Classifier: Topic :: Database
Classifier: Topic :: Scientific/Engineering
Classifier: License :: OSI Approved :: Apache Software License
Classifier: Programming Language :: Python
Classifier: Programming Language :: Python :: 3.6
Classifier: Programming Language :: Python :: 3.7
Classifier: Programming Language :: Python :: 3.8
Classifier: Programming Language :: Python :: 3.9
Classifier: Programming Language :: Python :: 3.10
Classifier: Programming Language :: Python :: 3.11
Classifier: Programming Language :: Python :: 3.12
License-File: LICENSE.txt
Provides-Extra: test
Requires-Dist: pytest; extra == "test"
Requires-Dist: Cython==3.0.11; extra == "test"
Requires-Dist: setuptools; extra == "test"
Provides-Extra: docs
Requires-Dist: sphinx; extra == "docs"
Requires-Dist: nvidia_sphinx_theme; extra == "docs"
Dynamic: license-file
